nonebot_plugin_aichat/__init__.py
nonebot_plugin_aichat/config.py
nonebot_plugin_aichat/entity/__init__.py
nonebot_plugin_aichat/entity/Chat.py
nonebot_plugin_aichat/flags.py
nonebot_plugin_aichat-0.1.0.dev5.dist-info/LICENSE
nonebot_plugin_aichat-0.1.0.dev5.dist-info/METADATA
nonebot_plugin_aichat-0.1.0.dev5.dist-info/WHEEL
nonebot_plugin_aichat-0.1.0.dev5.dist-info/RECORD
