Metadata-Version: 2.1
Name: nonebot_plugin_aichat
Version: 0.1.0.dev5
Summary: 
Author: Expliyh
Author-email: expliyh@outlook.com
Requires-Python: >=3.11,<4.0
Classifier: Programming Language :: Python :: 3
Classifier: Programming Language :: Python :: 3.11
Classifier: Programming Language :: Python :: 3.12
Classifier: Programming Language :: Python :: 3.13
Requires-Dist: nonebot2 (>=2.3.3,<3.0.0)
Requires-Dist: pydantic (>=1.10.18,<2.0.0)
Requires-Dist: pypika-tortoise (>=0.1.6,<0.2.0)
Requires-Dist: tortoise-orm (>=0.20.0,<0.21.0)
